MANIFEST.in
README.MD
setup.py
zfun/__init__.py
zfun/bio.py
zfun/com.py
zfun/db.py
zfun/funs.py
zfun/test.py
zfun/web.py
zfun.egg-info/PKG-INFO
zfun.egg-info/SOURCES.txt
zfun.egg-info/dependency_links.txt
zfun.egg-info/requires.txt
zfun.egg-info/top_level.txt