Metadata-Version: 2.1
Name: zfun
Version: 3.0.6
Summary: 个人常用函数库
Home-page: https://github.com/zhenghy/zpy
Author: Haiyang Zheng
Author-email: wnfdsfy@gmail.com
License: MIT
Keywords: common,function,class
Platform: any
Requires-Dist: pymysql
Requires-Dist: dash_mantine_components
Requires-Dist: dash_tabulator
Requires-Dist: PyPDF2
Requires-Dist: pywinrm
Requires-Dist: sqlalchemy
Requires-Dist: fastapi
Requires-Dist: aiofiles
Requires-Dist: reportlab
Requires-Dist: pandas
